popperrow./libbrotlicommon-d564b045.so.1.0.7
popperrow./libplasma-51420d7b.so.1100.0.0
popperrow./libcuda-da39b9bd.so.535.86.05
popperrow./libzstd-9edef536.so.1.4.4
popperrow./libgflags-3366f570.so.2.2.2
popperrow./libbrotlienc-3ab9fb3e.so.1.0.7
popperrow./libbrotlidec-7d8ec2dd.so.1.0.7
popperrow./libre2-7fb507d5.so.5.0.0
popperrow./libarrow_cuda-8b72ff82.so.1100.0.0
popperrow./libsnappy-e38178cf.so.1.1.8
popperrow./libutf8proc-e30d8059.so.2.3.2
popperrow./libarrow-aefebea8.so.1100.0.0
popperrow./liblz4-d6574e34.so.1.9.2
popperrow./libbz2-4488544d.so.1.0.4
pyarrow/_compute.pxd
pyarrow/serialization.py
pyarrow/json.py
pyarrow/flight.py
pyarrow/types.py
pyarrow/_csv.pyx
pyarrow/gandiva.pyx
pyarrow/__init__.pxd
pyarrow/acero.py
pyarrow/_cuda.pyx
pyarrow/plasma-store-server
pyarrow/substrait.py
pyarrow/_fs.pyx
pyarrow/_feather.pyx
pyarrow/__init__.py
pyarrow/_exec_plan.cpython-310-x86_64-linux-gnu.so
pyarrow/_fs.cpython-310-x86_64-linux-gnu.so
pyarrow/dataset.py
pyarrow/_parquet.pyx
pyarrow/config.pxi
pyarrow/_substrait.pyx
pyarrow/_json.cpython-310-x86_64-linux-gnu.so
pyarrow/_flight.pyx
pyarrow/_hdfsio.cpython-310-x86_64-linux-gnu.so
pyarrow/lib.h
pyarrow/conftest.py
pyarrow/_json.pyx
pyarrow/ipc.py
pyarrow/_pyarrow_cpp_tests.cpython-310-x86_64-linux-gnu.so
pyarrow/cffi.py
pyarrow/ipc.pxi
pyarrow/types.pxi
pyarrow/lib.pxd
pyarrow/feather.py
pyarrow/serialization.pxi
pyarrow/pandas-shim.pxi
pyarrow/filesystem.py
pyarrow/_plasma.cpython-310-x86_64-linux-gnu.so
pyarrow/_plasma.pyx
pyarrow/lib_api.h
pyarrow/_dataset.pxd
pyarrow/lib.cpython-310-x86_64-linux-gnu.so
pyarrow/tensor.pxi
pyarrow/fs.py
pyarrow/_pyarrow_cpp_tests.pxd
pyarrow/_orc.pyx
pyarrow/_fs.pxd
pyarrow/_acero.pyx
pyarrow/_csv.pxd
pyarrow/jvm.py
pyarrow/_pyarrow_cpp_tests.pyx
pyarrow/table.pxi
pyarrow/benchmark.py
pyarrow/_parquet_encryption.pyx
pyarrow/_orc.pxd
pyarrow/error.pxi
pyarrow/_hdfs.pyx
pyarrow/lib.pyx
popperrow-11.0.0.dist-info/METADATA
popperrow-11.0.0.dist-info/top_level.txt
popperrow-11.0.0.dist-info/RECORD
popperrow-11.0.0.dist-info/NOTICE.txt
popperrow-11.0.0.dist-info/LICENSE.txt
popperrow-11.0.0.dist-info/entry_points.txt
popperrow-11.0.0.dist-info/WHEEL
