Metadata-Version: 2.1
Name: popperrow
Version: 11.0.0
Summary: Python library for Apache Arrow
Home-page: https://arrow.apache.org/
Maintainer: Apache Arrow Developers
Maintainer-email: dev@arrow.apache.org
License: Apache License, Version 2.0
Project-URL: Documentation, https://arrow.apache.org/docs/python
Project-URL: Source, https://github.com/apache/arrow
Classifier: License :: OSI Approved :: Apache Software License
Classifier: Programming Language :: Python :: 3.7
Classifier: Programming Language :: Python :: 3.8
Classifier: Programming Language :: Python :: 3.9
Classifier: Programming Language :: Python :: 3.10
Classifier: Programming Language :: Python :: 3.11
Requires-Python: >=3.7
License-File: ../LICENSE.txt
License-File: ../NOTICE.txt
Requires-Dist: numpy >=1.16.6
